test/__init__.py
test/run3.py
test/run4.py
test/run6.py
test/test_Cramer.py
test/test_MR_Cramer.py
test/test_config.py
test/test_getPrice.py
test/test_parameters.py
test/test_parse_value.py
test/test_redis_cache.py
test/test_sessions.py
test/test_utils.py
test/test_workflow.py
test/test_workflow2.py
vmwvro2/__init__.py
vmwvro2/config.py
vmwvro2/parameters.py
vmwvro2/sessions.py
vmwvro2/settings.py
vmwvro2/utils.py
vmwvro2/workflow.py
vmwvro2-0.1.12.dist-info/LICENSE
vmwvro2-0.1.12.dist-info/METADATA
vmwvro2-0.1.12.dist-info/WHEEL
vmwvro2-0.1.12.dist-info/top_level.txt
vmwvro2-0.1.12.dist-info/RECORD
