Metadata-Version: 2.1
Name: vmwvro2
Version: 0.1.12
Summary: REST lib for VMWARE vRO
Home-page: http://github.com/JoseIbanez/vmwvro2
Author: Jose Ibanez
Author-email: ibanez.j@gmail.com
License: MIT License
Platform: UNKNOWN
Classifier: Programming Language :: Python :: 3.6
Classifier: License :: OSI Approved :: MIT License
Classifier: Operating System :: OS Independent
Requires-Dist: requests
Requires-Dist: PyYAML (>=5.1)
Requires-Dist: PySocks
Requires-Dist: parameterized
Requires-Dist: redis
